{
  "version": "3.5.0",
  "flags": {},
  "shapes": [
    {
      "label": "banana",
      "points": [
        [
          20,
          48
        ],
        [
          333,
          174
        ]
      ],
      "shape_type": "rectangle",
      "line_color": null,
      "fill_color": null
    },
    {
      "label": "banana",
      "points": [
        [
          172,
          67
        ],
        [
          395,
          282
        ]
      ],
      "shape_type": "rectangle",
      "line_color": null,
      "fill_color": null
    },
    {
      "label": "banana",
      "points": [
        [
          57,
          76
        ],
        [
          349,
          225
        ]
      ],
      "shape_type": "rectangle",
      "line_color": null,
      "fill_color": null
    }
  ],
  "lineColor": [
    0,
    255,
    0,
    128
  ],
  "fillColor": [
    255,
    0,
    0,
    128
  ],
  "imagePath": "banana_66.jpg",
  "imageData": null
}